recommender_pkg/__init__.py
recommender_pkg/evaluation.py
recommender_pkg/explicit.py
recommender_pkg/implicit.py
recommender_pkg/metrics.py
recommender_pkg/model_selection.py
recommender_pkg/preprocessing.py
recommender_pkg/recommenders.py
recpkg/__init__.py
recpkg/evaluation.py
recpkg/explicit.py
recpkg/implicit.py
recpkg/metrics.py
recpkg/model_selection.py
recpkg/preprocessing.py
recpkg/recommenders.py
recommender_pkg-0.0.6.dist-info/LICENSE
recommender_pkg-0.0.6.dist-info/METADATA
recommender_pkg-0.0.6.dist-info/WHEEL
recommender_pkg-0.0.6.dist-info/top_level.txt
recommender_pkg-0.0.6.dist-info/RECORD
