Metadata-Version: 2.1
Name: recommender-pkg
Version: 0.0.6
Summary: A small recommender package
Home-page: https://github.com/mianuddin/csc492_recommender_pkg
Author: Mian Uddin
Author-email: mianuddin@gmail.com
License: UNKNOWN
Platform: UNKNOWN
License-File: LICENSE
Requires-Dist: numpy
Requires-Dist: pandas
Requires-Dist: seaborn
Requires-Dist: scikit-learn
Requires-Dist: tensorflow (>=2.5.0rc0)
Requires-Dist: tqdm
